tradestrategy/TradeStrategizor.py
tradestrategy/__init__.py
persuader_technology_automata_trade_strategy-0.1.1.dist-info/LICENSE
persuader_technology_automata_trade_strategy-0.1.1.dist-info/METADATA
persuader_technology_automata_trade_strategy-0.1.1.dist-info/WHEEL
persuader_technology_automata_trade_strategy-0.1.1.dist-info/top_level.txt
persuader_technology_automata_trade_strategy-0.1.1.dist-info/RECORD
