Metadata-Version: 2.1
Name: persuader-technology-automata-trade-strategy
Version: 0.1.1
Summary: Automata Trade Strategy
Author: Persuader Technology
Author-email: software@persuader.technology
License: UNLICENSE
Classifier: Programming Language :: Python :: 3
License-File: LICENSE
Requires-Dist: persuader-technology-automata-core (>=0.6.0)
